{"v":3,"stories":{"basics--default":{"id":"basics--default","name":"Default","title":"Basics","importPath":"./stories/Basics.stories.tsx","tags":["story"],"kind":"Basics","story":"Default","parameters":{"__id":"basics--default","docsOnly":false,"fileName":"./stories/Basics.stories.tsx"}},"basics--disabled":{"id":"basics--disabled","name":"Disabled","title":"Basics","importPath":"./stories/Basics.stories.tsx","tags":["story"],"kind":"Basics","story":"Disabled","parameters":{"__id":"basics--disabled","docsOnly":false,"fileName":"./stories/Basics.stories.tsx"}},"basics--steps":{"id":"basics--steps","name":"Steps","title":"Basics","importPath":"./stories/Basics.stories.tsx","tags":["story"],"kind":"Basics","story":"Steps","parameters":{"__id":"basics--steps","docsOnly":false,"fileName":"./stories/Basics.stories.tsx"}},"basics--hours":{"id":"basics--hours","name":"Hours","title":"Basics","importPath":"./stories/Basics.stories.tsx","tags":["story"],"kind":"Basics","story":"Hours","parameters":{"__id":"basics--hours","docsOnly":false,"fileName":"./stories/Basics.stories.tsx"}},"basics--format":{"id":"basics--format","name":"Format","title":"Basics","importPath":"./stories/Basics.stories.tsx","tags":["story"],"kind":"Basics","story":"Format","parameters":{"__id":"basics--format","docsOnly":false,"fileName":"./stories/Basics.stories.tsx"}}}}
